femtools/BTS.py
femtools/CA.py
femtools/DMI.py
femtools/MIG.py
femtools/__init__.py
femtools-0.0.5.dist-info/LICENSE
femtools-0.0.5.dist-info/METADATA
femtools-0.0.5.dist-info/WHEEL
femtools-0.0.5.dist-info/top_level.txt
femtools-0.0.5.dist-info/RECORD
