Metadata-Version: 2.1
Name: femtools
Version: 0.0.5
Summary: Forecast-elicitation-Mechanism
Home-page: https://github.com/Hermera/Forecast-elicitation-Mechanism
Author: thaddywu
Author-email: thaddywu@gmail.com
License: UNKNOWN
Platform: UNKNOWN
Classifier: Programming Language :: Python :: 3
Classifier: License :: OSI Approved :: MIT License
Classifier: Operating System :: OS Independent
